MANIFEST.in
README.rst
setup.py
GaitAnalysisToolKit.egg-info/PKG-INFO
GaitAnalysisToolKit.egg-info/SOURCES.txt
GaitAnalysisToolKit.egg-info/dependency_links.txt
GaitAnalysisToolKit.egg-info/requires.txt
GaitAnalysisToolKit.egg-info/top_level.txt
bin/dflowdata
docs/021-bad-idxs-zoom.png
docs/Makefile
docs/conf.py
docs/constant-markers.png
docs/d-flow-time-stamp-diff.png
docs/gait.rst
docs/gaitanalysis.rst
docs/hbm-missing.png
docs/index.rst
docs/linear-interpolation.png
docs/motek.rst
gaitanalysis/__init__.py
gaitanalysis/controlid.py
gaitanalysis/gait.py
gaitanalysis/markers.py
gaitanalysis/motek.py
gaitanalysis/utils.py
gaitanalysis/version.py
gaitanalysis/octave/2d_inverse_dynamics/leg2d.m
gaitanalysis/octave/2d_inverse_dynamics/myfiltfilt.m
gaitanalysis/octave/2d_inverse_dynamics/rtfilter.m
gaitanalysis/octave/2d_inverse_dynamics/test/rawdata.txt
gaitanalysis/octave/2d_inverse_dynamics/test/refresults.mat
gaitanalysis/octave/2d_inverse_dynamics/test/test.m
gaitanalysis/octave/inertial_compensation/compensation.m
gaitanalysis/octave/inertial_compensation/inertial_compensation.m
gaitanalysis/octave/inertial_compensation/transformation.m
gaitanalysis/octave/inertial_compensation/test/9.10.2013Stationary0001.txt
gaitanalysis/octave/inertial_compensation/test/compensation_function_test.m
gaitanalysis/octave/mmat/license.txt
gaitanalysis/octave/mmat/mmat.m
gaitanalysis/octave/soder/soder.m
gaitanalysis/octave/soder/test_soder.m
gaitanalysis/octave/soder/time_soder.m
gaitanalysis/octave/time_delay/time_delay.m
gaitanalysis/tests/__init__.py
gaitanalysis/tests/test_controlid.py
gaitanalysis/tests/test_gait.py
gaitanalysis/tests/test_markers.py
gaitanalysis/tests/test_motek.py
gaitanalysis/tests/utils.py
gaitanalysis/tests/data/example_extract_events_from_record_module.txt
gaitanalysis/tests/data/example_vertical_grf.csv
gaitanalysis/tests/data/meta-sample-full.yml
gaitanalysis/tests/data/meta_events_example.yml
gaitanalysis/tests/data/treadmill-speed.csv