Metadata-Version: 2.1
Name: GaitAnalysisToolKit
Version: 0.2.0
Summary: Various tools for gait analysis used at the Cleveland State University Human Motion and Control Lab.
Home-page: http://github.com/csu-hmc/GaitAnalysisToolKit
Author: Jason K. Moore
Author-email: moorepants@gmail.com
License: LICENSE.txt
Platform: UNKNOWN
Classifier: Development Status :: 4 - Beta
Classifier: Intended Audience :: Science/Research
Classifier: Operating System :: OS Independent
Classifier: Programming Language :: Python :: 2.7
Classifier: Programming Language :: Python :: 3.7
Classifier: Topic :: Scientific/Engineering :: Physics
Provides-Extra: doc
